pyprintf/__init__.py
pyprintf/core.py
pyprintf-0.0.8.dist-info/licenses/LICENSE
pyprintf-0.0.8.dist-info/METADATA
pyprintf-0.0.8.dist-info/WHEEL
pyprintf-0.0.8.dist-info/top_level.txt
pyprintf-0.0.8.dist-info/RECORD
