Metadata-Version: 2.4
Name: pyprintf
Version: 0.0.8
Summary: A lightweight, Open Source pyprintf sprintf() implementation written in Python
Author-email: Zsolt Oroszlány <hello@playfulsparkle.com>
Maintainer-email: Zsolt Oroszlány <hello@playfulsparkle.com>
License: BSD-3-Clause
Project-URL: Bug Tracker, https://github.com/playfulsparkle/pyprintf/issues
Project-URL: Change Log, https://github.com/playfulsparkle/pyprintf/blob/main/CHANGELOG.md
Project-URL: Github, https://github.com/playfulsparkle/pyprintf
Project-URL: Homepage, https://github.com/playfulsparkle/pyprintf
Keywords: pyprintf,sprintf,parser,python,formatting
Classifier: Development Status :: 5 - Production/Stable
Classifier: Intended Audience :: Developers
Classifier: Intended Audience :: Information Technology
Classifier: Natural Language :: English
Classifier: Operating System :: OS Independent
Classifier: Programming Language :: Python :: 3
Classifier: Programming Language :: Python :: 3.10
Classifier: Programming Language :: Python :: 3.12
Classifier: Programming Language :: Python :: 3.13
Classifier: Topic :: Software Development :: Libraries
Classifier: Topic :: Software Development :: Libraries :: Python Modules
Classifier: Topic :: Text Processing :: General
Classifier: Typing :: Typed
Classifier: Framework :: Pytest
Requires-Python: >=3.10
License-File: LICENSE
Requires-Dist: typing-extensions>=4.0.0; python_version < "3.11"
Provides-Extra: test
Requires-Dist: pytest>=8.3.0; extra == "test"
Requires-Dist: pytest-cov>=4.1.0; extra == "test"
Requires-Dist: flake8>=7.0.0; extra == "test"
Dynamic: license-file
